openmc_regular_mesh_plotter/__init__.py
openmc_regular_mesh_plotter/_version.py
openmc_regular_mesh_plotter/core.py
openmc_regular_mesh_plotter-1.2.2.dist-info/LICENSE.txt
openmc_regular_mesh_plotter-1.2.2.dist-info/METADATA
openmc_regular_mesh_plotter-1.2.2.dist-info/WHEEL
openmc_regular_mesh_plotter-1.2.2.dist-info/top_level.txt
openmc_regular_mesh_plotter-1.2.2.dist-info/RECORD
