Metadata-Version: 2.1
Name: openmc_regular_mesh_plotter
Version: 1.2.2
Summary: A Python package for creating plots of OpenMC regular mesh tallies with the underlying geometry
Author-email: Jonathan Shimwell <mail@jshimwell.com>
License: MIT License
Project-URL: Homepage, https://github.com/fusion-energy/openmc_regular_mesh_plotter
Project-URL: Bug Tracker, https://github.com/fusion-energy/openmc_regular_mesh_plotter/issues
Keywords: regular,mesh,openmc,tally,plot,slice,geometry
Classifier: Programming Language :: Python :: 3
Classifier: License :: OSI Approved :: MIT License
Classifier: Operating System :: OS Independent
Requires-Python: >=3.8
License-File: LICENSE.txt
Requires-Dist: numpy >=1.21.1
Requires-Dist: matplotlib >=3.4.2
Requires-Dist: setuptools-scm
Provides-Extra: tests
Requires-Dist: pytest ; extra == 'tests'
